lambdata_matthew/__init__.py
lambdata_matthew/get_na.py
matthewdata-0.0.2.dist-info/LICENSE
matthewdata-0.0.2.dist-info/METADATA
matthewdata-0.0.2.dist-info/WHEEL
matthewdata-0.0.2.dist-info/top_level.txt
matthewdata-0.0.2.dist-info/RECORD
