Metadata-Version: 2.1
Name: matthewdata
Version: 0.0.2
Summary: collection of data
Home-page: https://github.com/matthew-sessions/lambdata
Author: matthew
License: UNKNOWN
Platform: UNKNOWN
Classifier: Programming Language :: Python :: 3
Classifier: License :: OSI Approved :: MIT License
Classifier: Operating System :: OS Independent
Requires-Python: >=3.5
